slack_ipython/__init__.py
slack_ipython/config.py
slack_ipython/kernel_manager.py
slack_ipython/launch_kernel.py
slack_ipython/main.py
slack_ipython/utils.py
slack_ipython-0.0.3.dist-info/LICENSE
slack_ipython-0.0.3.dist-info/METADATA
slack_ipython-0.0.3.dist-info/WHEEL
slack_ipython-0.0.3.dist-info/entry_points.txt
slack_ipython-0.0.3.dist-info/top_level.txt
slack_ipython-0.0.3.dist-info/RECORD
