Metadata-Version: 2.1
Name: slack-ipython
Version: 0.0.3
Summary: A Python Slack bot through IPython
Home-page: https://github.com/ricklamers/slack-ipython
Author: R. Lamers
Author-email: ricklamers@gmail.com
License: UNKNOWN
Project-URL: Bug Tracker, https://github.com/ricklamers/slack-ipython/issues
Platform: UNKNOWN
Classifier: Programming Language :: Python :: 3
Classifier: License :: OSI Approved :: Apache Software License
Classifier: Operating System :: OS Independent
Requires-Python: >=3.6
License-File: LICENSE
Requires-Dist: ipykernel
Requires-Dist: matplotlib
Requires-Dist: slack-bolt
Requires-Dist: python-dotenv
Requires-Dist: snakemq
